namsmd/__init__.py
namsmd/directlink.py
namsmd/nsfw_sites/__init__.py
namsmd/nsfw_sites/hentaivn.py
namsmd/nsfw_sites/iwara_api.py
namsmd/nsfw_sites/khotruyencc.py
namsmd/sfw_sites/__init__.py
namsmd/sfw_sites/gdrive.py
namsmd/sfw_sites/rgcolab.py
namsmd-0.0.2.dist-info/METADATA
namsmd-0.0.2.dist-info/WHEEL
namsmd-0.0.2.dist-info/top_level.txt
namsmd-0.0.2.dist-info/RECORD
