Metadata-Version: 2.1
Name: namsmd
Version: 0.0.2
Summary: Sites Media Downloader
Author: Nam Nguyen
Author-email: nnamnguyenn@07kpq.onmicrosoft.com
Keywords: python,first package
Classifier: Development Status :: 3 - Alpha
Classifier: Intended Audience :: Education
Classifier: Programming Language :: Python :: 3
Classifier: Operating System :: Microsoft :: Windows
Requires-Dist: lxml
Requires-Dist: beautifulsoup4
